Metadata-Version: 2.1
Name: py-dispatch
Version: 0.0.3
Summary: A low information-redundancy cli framework.
Home-page: https://github.com/harrybrwn/dispatch
Author: Harrison Brown
Author-email: harrybrown98@gmail.com
License: Apache 2.0
Download-URL: https://github.com/harrybrwn/dispatch/archive/v0.0.3.tar.gz
Keywords: command line,cli,framework,tool,simple
Platform: UNKNOWN
Classifier: Programming Language :: Python :: 3
Classifier: Programming Language :: Python :: 3.7
Classifier: License :: OSI Approved :: Apache Software License
Classifier: Operating System :: OS Independent
